kotlin version: 2.0.21
error message: org.jetbrains.kotlin.codegen.CompilationException: Back-end (JVM) Internal error: Couldn't transform method node:
uploadAssembly (Lcom/example/rocketplan_android/data/local/entity/ImageProcessorAssemblyEntity;Lkotlin/coroutines/Continuation;)Ljava/lang/Object;:
    // annotable parameter count: 2 (visible)
    // annotable parameter count: 2 (invisible)
    TRYCATCHBLOCK L0 L1 L2 java/lang/Exception
    TRYCATCHBLOCK L3 L4 L5 java/lang/Exception
   L6
   L7
    LINENUMBER 282 L7
   L8
   L3
    NOP
   L9
    LINENUMBER 283 L9
    LDC "ImgProcessorQueueMgr"
    ALOAD 1
    INVOKEVIRTUAL com/example/rocketplan_android/data/local/entity/ImageProcessorAssemblyEntity.getAssemblyId ()Ljava/lang/String;
    INVOKEDYNAMIC makeConcatWithConstants(Ljava/lang/String;)Ljava/lang/String; [
      // handle kind 0x6 : INVOKESTATIC
      java/lang/invoke/StringConcatFactory.makeConcatWithConstants(Ljava/lang/invoke/MethodHandles$Lookup;Ljava/lang/String;Ljava/lang/invoke/MethodType;Ljava/lang/String;[Ljava/lang/Object;)Ljava/lang/invoke/CallSite;
      // arguments:
      "\ud83d\udcf8 Uploading assembly \u0001"
    ]
    INVOKESTATIC android/util/Log.d (Ljava/lang/String;Ljava/lang/String;)I
    POP
   L10
    LINENUMBER 286 L10
    ALOAD 0
    GETFIELD com/example/rocketplan_android/data/queue/ImageProcessorQueueManager.uploadStore : Lcom/example/rocketplan_android/data/storage/ImageProcessorUploadStore;
    ALOAD 1
    INVOKEVIRTUAL com/example/rocketplan_android/data/local/entity/ImageProcessorAssemblyEntity.getAssemblyId ()Ljava/lang/String;
    INVOKEVIRTUAL com/example/rocketplan_android/data/storage/ImageProcessorUploadStore.read (Ljava/lang/String;)Lcom/example/rocketplan_android/data/storage/StoredUploadData;
    ASTORE 3
   L11
   L12
    LINENUMBER 287 L12
    ALOAD 3
    IFNONNULL L13
   L14
    LINENUMBER 288 L14
    LDC "Upload data missing - cannot retry without stored credentials"
    ASTORE 4
   L15
   L16
    LINENUMBER 289 L16
    LDC "ImgProcessorQueueMgr"
    ALOAD 1
    INVOKEVIRTUAL com/example/rocketplan_android/data/local/entity/ImageProcessorAssemblyEntity.getAssemblyId ()Ljava/lang/String;
    INVOKEDYNAMIC makeConcatWithConstants(Ljava/lang/String;)Ljava/lang/String; [
      // handle kind 0x6 : INVOKESTATIC
      java/lang/invoke/StringConcatFactory.makeConcatWithConstants(Ljava/lang/invoke/MethodHandles$Lookup;Ljava/lang/String;Ljava/lang/invoke/MethodType;Ljava/lang/String;[Ljava/lang/Object;)Ljava/lang/invoke/CallSite;
      // arguments:
      "\u274c No upload data for assembly \u0001"
    ]
    INVOKESTATIC android/util/Log.e (Ljava/lang/String;Ljava/lang/String;)I
    POP
   L17
    LINENUMBER 292 L17
    ALOAD 0
    ALOAD 1
    INVOKEVIRTUAL com/example/rocketplan_android/data/local/entity/ImageProcessorAssemblyEntity.getAssemblyId ()Ljava/lang/String;
    GETSTATIC com/example/rocketplan_android/data/local/entity/AssemblyStatus.FAILED : Lcom/example/rocketplan_android/data/local/entity/AssemblyStatus;
    ALOAD 4
    ALOAD 2
    ICONST_0
    INVOKESTATIC kotlin/jvm/internal/InlineMarker.mark (I)V
    INVOKESPECIAL com/example/rocketplan_android/data/queue/ImageProcessorQueueManager.updateAssemblyStatus (Ljava/lang/String;Lcom/example/rocketplan_android/data/local/entity/AssemblyStatus;Ljava/lang/String;Lkotlin/coroutines/Continuation;)Ljava/lang/Object;
    ICONST_1
    INVOKESTATIC kotlin/jvm/internal/InlineMarker.mark (I)V
    POP
   L18
    LINENUMBER 294 L18
    ALOAD 0
    ALOAD 1
    INVOKEVIRTUAL com/example/rocketplan_android/data/local/entity/ImageProcessorAssemblyEntity.getAssemblyId ()Ljava/lang/String;
    NOP
    ICONST_0
    ALOAD 4
    ALOAD 2
    ICONST_0
    INVOKESTATIC kotlin/jvm/internal/InlineMarker.mark (I)V
    INVOKESPECIAL com/example/rocketplan_android/data/queue/ImageProcessorQueueManager.onAssemblyCompleted (Ljava/lang/String;ZLjava/lang/String;Lkotlin/coroutines/Continuation;)Ljava/lang/Object;
    ICONST_1
    INVOKESTATIC kotlin/jvm/internal/InlineMarker.mark (I)V
    POP
   L19
    LINENUMBER 295 L19
    GETSTATIC kotlin/Unit.INSTANCE : Lkotlin/Unit;
    ARETURN
   L20
   L21
   L13
   L22
   L23
    LINENUMBER 299 L23
    ALOAD 0
    GETFIELD com/example/rocketplan_android/data/queue/ImageProcessorQueueManager.dao : Lcom/example/rocketplan_android/data/local/dao/ImageProcessorDao;
    ALOAD 1
    INVOKEVIRTUAL com/example/rocketplan_android/data/local/entity/ImageProcessorAssemblyEntity.getAssemblyId ()Ljava/lang/String;
    ALOAD 2
    ICONST_0
    INVOKESTATIC kotlin/jvm/internal/InlineMarker.mark (I)V
    INVOKEINTERFACE com/example/rocketplan_android/data/local/dao/ImageProcessorDao.getPhotosByAssemblyUuid (Ljava/lang/String;Lkotlin/coroutines/Continuation;)Ljava/lang/Object; (itf)
    ICONST_1
    INVOKESTATIC kotlin/jvm/internal/InlineMarker.mark (I)V
    CHECKCAST java/util/List
    ASTORE 4
   L24
   L25
    LINENUMBER 302 L25
    ALOAD 0
    ALOAD 1
    ALOAD 4
    ALOAD 2
    ICONST_0
    INVOKESTATIC kotlin/jvm/internal/InlineMarker.mark (I)V
    INVOKESPECIAL com/example/rocketplan_android/data/queue/ImageProcessorQueueManager.reconcileWithBackendStatus (Lcom/example/rocketplan_android/data/local/entity/ImageProcessorAssemblyEntity;Ljava/util/List;Lkotlin/coroutines/Continuation;)Ljava/lang/Object;
    ICONST_1
    INVOKESTATIC kotlin/jvm/internal/InlineMarker.mark (I)V
    CHECKCAST java/lang/Boolean
    INVOKEVIRTUAL java/lang/Boolean.booleanValue ()Z
    IFEQ L26
   L27
    LINENUMBER 303 L27
    GETSTATIC kotlin/Unit.INSTANCE : Lkotlin/Unit;
    ARETURN
   L28
   L26
   L29
   L30
    LINENUMBER 308 L30
    ALOAD 0
    ALOAD 1
    INVOKEVIRTUAL com/example/rocketplan_android/data/local/entity/ImageProcessorAssemblyEntity.getAssemblyId ()Ljava/lang/String;
    GETSTATIC com/example/rocketplan_android/data/local/entity/AssemblyStatus.UPLOADING : Lcom/example/rocketplan_android/data/local/entity/AssemblyStatus;
    ACONST_NULL
    ALOAD 2
    ICONST_0
    INVOKESTATIC kotlin/jvm/internal/InlineMarker.mark (I)V
    INVOKESPECIAL com/example/rocketplan_android/data/queue/ImageProcessorQueueManager.updateAssemblyStatus (Ljava/lang/String;Lcom/example/rocketplan_android/data/local/entity/AssemblyStatus;Ljava/lang/String;Lkotlin/coroutines/Continuation;)Ljava/lang/Object;
    ICONST_1
    INVOKESTATIC kotlin/jvm/internal/InlineMarker.mark (I)V
    POP
   L31
    LINENUMBER 310 L31
    ALOAD 4
    CHECKCAST java/lang/Iterable
    ASTORE 6
    NOP
   L32
    ICONST_0
    ISTORE 7
   L33
    LINENUMBER 748 L33
    ALOAD 6
    ASTORE 8
    NEW java/util/ArrayList
    DUP
    INVOKESPECIAL java/util/ArrayList.<init> ()V
    CHECKCAST java/util/Collection
    ASTORE 9
   L34
    ICONST_0
    ISTORE 10
   L35
    LINENUMBER 749 L35
    ALOAD 8
    INVOKEINTERFACE java/lang/Iterable.iterator ()Ljava/util/Iterator; (itf)
    ASTORE 11
   L36
    ALOAD 11
    INVOKEINTERFACE java/util/Iterator.hasNext ()Z (itf)
    IFEQ L37
    ALOAD 11
    INVOKEINTERFACE java/util/Iterator.next ()Ljava/lang/Object; (itf)
    ASTORE 12
   L38
    ALOAD 12
    CHECKCAST com/example/rocketplan_android/data/local/entity/ImageProcessorPhotoEntity
    ASTORE 13
   L39
    ICONST_0
    ISTORE 14
   L40
    LINENUMBER 310 L40
    ALOAD 13
    INVOKEVIRTUAL com/example/rocketplan_android/data/local/entity/ImageProcessorPhotoEntity.getStatus ()Ljava/lang/String;
    GETSTATIC com/example/rocketplan_android/data/local/entity/PhotoStatus.PENDING : Lcom/example/rocketplan_android/data/local/entity/PhotoStatus;
    INVOKEVIRTUAL com/example/rocketplan_android/data/local/entity/PhotoStatus.getValue ()Ljava/lang/String;
    INVOKESTATIC kotlin/jvm/internal/Intrinsics.areEqual (Ljava/lang/Object;Ljava/lang/Object;)Z
    NOP
    GOTO L41
   L42
   L43
   L41
    INVOKESTATIC kotlin/coroutines/jvm/internal/Boxing.boxBoolean (Z)Ljava/lang/Boolean;
   L44
    LINENUMBER 749 L44
    CHECKCAST java/lang/Boolean
    INVOKEVIRTUAL java/lang/Boolean.booleanValue ()Z
    IFEQ L36
    ALOAD 9
    ALOAD 12
    INVOKEINTERFACE java/util/Collection.add (Ljava/lang/Object;)Z (itf)
    POP
   L45
    GOTO L36
   L37
    LINENUMBER 750 L37
    ALOAD 9
   L46
    CHECKCAST java/util/List
   L47
    LINENUMBER 748 L47
    NOP
    GOTO L48
   L49
   L50
   L48
   L51
    LINENUMBER 310 L51
    ASTORE 5
   L52
   L53
    LINENUMBER 312 L53
    ALOAD 5
    INVOKEINTERFACE java/util/List.isEmpty ()Z (itf)
    IFEQ L54
   L55
    LINENUMBER 313 L55
    LDC "ImgProcessorQueueMgr"
    ALOAD 1
    INVOKEVIRTUAL com/example/rocketplan_android/data/local/entity/ImageProcessorAssemblyEntity.getAssemblyId ()Ljava/lang/String;
    INVOKEDYNAMIC makeConcatWithConstants(Ljava/lang/String;)Ljava/lang/String; [
      // handle kind 0x6 : INVOKESTATIC
      java/lang/invoke/StringConcatFactory.makeConcatWithConstants(Ljava/lang/invoke/MethodHandles$Lookup;Ljava/lang/String;Ljava/lang/invoke/MethodType;Ljava/lang/String;[Ljava/lang/Object;)Ljava/lang/invoke/CallSite;
      // arguments:
      "\u2705 All photos already uploaded for assembly \u0001"
    ]
    INVOKESTATIC android/util/Log.d (Ljava/lang/String;Ljava/lang/String;)I
    POP
   L56
    LINENUMBER 314 L56
    ALOAD 0
    ALOAD 1
    INVOKEVIRTUAL com/example/rocketplan_android/data/local/entity/ImageProcessorAssemblyEntity.getAssemblyId ()Ljava/lang/String;
    ALOAD 2
    ICONST_0
    INVOKESTATIC kotlin/jvm/internal/InlineMarker.mark (I)V
    INVOKESPECIAL com/example/rocketplan_android/data/queue/ImageProcessorQueueManager.checkIfAssemblyComplete (Ljava/lang/String;Lkotlin/coroutines/Continuation;)Ljava/lang/Object;
    ICONST_1
    INVOKESTATIC kotlin/jvm/internal/InlineMarker.mark (I)V
    POP
   L57
    LINENUMBER 315 L57
    GETSTATIC kotlin/Unit.INSTANCE : Lkotlin/Unit;
    ARETURN
   L58
   L54
   L59
   L60
    LINENUMBER 318 L60
    LDC "ImgProcessorQueueMgr"
    ALOAD 5
    INVOKEINTERFACE java/util/List.size ()I (itf)
    ALOAD 1
    INVOKEVIRTUAL com/example/rocketplan_android/data/local/entity/ImageProcessorAssemblyEntity.getAssemblyId ()Ljava/lang/String;
    INVOKEDYNAMIC makeConcatWithConstants(ILjava/lang/String;)Ljava/lang/String; [
      // handle kind 0x6 : INVOKESTATIC
      java/lang/invoke/StringConcatFactory.makeConcatWithConstants(Ljava/lang/invoke/MethodHandles$Lookup;Ljava/lang/String;Ljava/lang/invoke/MethodType;Ljava/lang/String;[Ljava/lang/Object;)Ljava/lang/invoke/CallSite;
      // arguments:
      "\ud83d\udce4 Uploading \u0001 photos for assembly \u0001"
    ]
    INVOKESTATIC android/util/Log.d (Ljava/lang/String;Ljava/lang/String;)I
    POP
   L61
    LINENUMBER 321 L61
    ICONST_0
    ISTORE 6
   L62
   L63
    LINENUMBER 322 L63
    ICONST_0
    ISTORE 7
   L64
   L65
    LINENUMBER 324 L65
    ALOAD 5
    INVOKEINTERFACE java/util/List.iterator ()Ljava/util/Iterator; (itf)
    ASTORE 8
   L66
   L67
    ALOAD 8
    INVOKEINTERFACE java/util/Iterator.hasNext ()Z (itf)
    IFEQ L68
    ALOAD 8
    INVOKEINTERFACE java/util/Iterator.next ()Ljava/lang/Object; (itf)
    CHECKCAST com/example/rocketplan_android/data/local/entity/ImageProcessorPhotoEntity
    ASTORE 9
   L69
   L70
    LINENUMBER 325 L70
   L71
   L0
    NOP
   L72
    LINENUMBER 326 L72
    ALOAD 0
    ALOAD 1
    ALOAD 9
    ALOAD 3
    INVOKEVIRTUAL com/example/rocketplan_android/data/storage/StoredUploadData.getProcessingUrl ()Ljava/lang/String;
    ALOAD 3
    INVOKEVIRTUAL com/example/rocketplan_android/data/storage/StoredUploadData.getApiKey ()Ljava/lang/String;
    ALOAD 2
    ICONST_0
    INVOKESTATIC kotlin/jvm/internal/InlineMarker.mark (I)V
    INVOKESPECIAL com/example/rocketplan_android/data/queue/ImageProcessorQueueManager.uploadPhoto (Lcom/example/rocketplan_android/data/local/entity/ImageProcessorAssemblyEntity;Lcom/example/rocketplan_android/data/local/entity/ImageProcessorPhotoEntity;Ljava/lang/String;Ljava/lang/String;Lkotlin/coroutines/Continuation;)Ljava/lang/Object;
    ICONST_1
    INVOKESTATIC kotlin/jvm/internal/InlineMarker.mark (I)V
    POP
   L73
    LINENUMBER 327 L73
    ILOAD 6
    IINC 6 1
    INVOKESTATIC kotlin/coroutines/jvm/internal/Boxing.boxInt (I)Ljava/lang/Integer;
    ASTORE 10
   L1
    GOTO L74
   L2
   L75
    LINENUMBER 328 L75
    ASTORE 11
   L76
   L77
    LINENUMBER 329 L77
    LDC "ImgProcessorQueueMgr"
    ALOAD 9
    INVOKEVIRTUAL com/example/rocketplan_android/data/local/entity/ImageProcessorPhotoEntity.getFileName ()Ljava/lang/String;
    INVOKEDYNAMIC makeConcatWithConstants(Ljava/lang/String;)Ljava/lang/String; [
      // handle kind 0x6 : INVOKESTATIC
      java/lang/invoke/StringConcatFactory.makeConcatWithConstants(Ljava/lang/invoke/MethodHandles$Lookup;Ljava/lang/String;Ljava/lang/invoke/MethodType;Ljava/lang/String;[Ljava/lang/Object;)Ljava/lang/invoke/CallSite;
      // arguments:
      "\u274c Failed to upload photo \u0001"
    ]
    ALOAD 11
    CHECKCAST java/lang/Throwable
    INVOKESTATIC android/util/Log.e (Ljava/lang/String;Ljava/lang/String;Ljava/lang/Throwable;)I
    POP
   L78
    LINENUMBER 330 L78
    ILOAD 7
    IINC 7 1
    POP
   L79
    LINENUMBER 331 L79
    ALOAD 0
    ALOAD 9
    INVOKEVIRTUAL com/example/rocketplan_android/data/local/entity/ImageProcessorPhotoEntity.getPhotoId ()Ljava/lang/String;
    GETSTATIC com/example/rocketplan_android/data/local/entity/PhotoStatus.FAILED : Lcom/example/rocketplan_android/data/local/entity/PhotoStatus;
    ALOAD 11
    INVOKEVIRTUAL java/lang/Exception.getMessage ()Ljava/lang/String;
    ALOAD 2
    ICONST_0
    INVOKESTATIC kotlin/jvm/internal/InlineMarker.mark (I)V
    INVOKESPECIAL com/example/rocketplan_android/data/queue/ImageProcessorQueueManager.updatePhotoStatus (Ljava/lang/String;Lcom/example/rocketplan_android/data/local/entity/PhotoStatus;Ljava/lang/String;Lkotlin/coroutines/Continuation;)Ljava/lang/Object;
    ICONST_1
    INVOKESTATIC kotlin/jvm/internal/InlineMarker.mark (I)V
    POP
    GETSTATIC kotlin/Unit.INSTANCE : Lkotlin/Unit;
    ASTORE 10
   L80
   L74
    ALOAD 10
    POP
   L81
    GOTO L67
   L68
   L82
   L83
    LINENUMBER 335 L83
    LDC "ImgProcessorQueueMgr"
    ILOAD 6
    ILOAD 7
    INVOKEDYNAMIC makeConcatWithConstants(II)Ljava/lang/String; [
      // handle kind 0x6 : INVOKESTATIC
      java/lang/invoke/StringConcatFactory.makeConcatWithConstants(Ljava/lang/invoke/MethodHandles$Lookup;Ljava/lang/String;Ljava/lang/invoke/MethodType;Ljava/lang/String;[Ljava/lang/Object;)Ljava/lang/invoke/CallSite;
      // arguments:
      "\ud83d\udcca Upload results: \u0001 succeeded, \u0001 failed"
    ]
    INVOKESTATIC android/util/Log.d (Ljava/lang/String;Ljava/lang/String;)I
    POP
   L84
    LINENUMBER 338 L84
    ALOAD 0
    ALOAD 1
    INVOKEVIRTUAL com/example/rocketplan_android/data/local/entity/ImageProcessorAssemblyEntity.getAssemblyId ()Ljava/lang/String;
    ALOAD 2
    ICONST_0
    INVOKESTATIC kotlin/jvm/internal/InlineMarker.mark (I)V
    INVOKESPECIAL com/example/rocketplan_android/data/queue/ImageProcessorQueueManager.checkIfAssemblyComplete (Ljava/lang/String;Lkotlin/coroutines/Continuation;)Ljava/lang/Object;
    ICONST_1
    INVOKESTATIC kotlin/jvm/internal/InlineMarker.mark (I)V
    POP
   L85
   L4
    GOTO L86
   L5
   L87
    LINENUMBER 339 L87
    ASTORE 3
   L88
   L89
    LINENUMBER 340 L89
    LDC "ImgProcessorQueueMgr"
    ALOAD 1
    INVOKEVIRTUAL com/example/rocketplan_android/data/local/entity/ImageProcessorAssemblyEntity.getAssemblyId ()Ljava/lang/String;
    INVOKEDYNAMIC makeConcatWithConstants(Ljava/lang/String;)Ljava/lang/String; [
      // handle kind 0x6 : INVOKESTATIC
      java/lang/invoke/StringConcatFactory.makeConcatWithConstants(Ljava/lang/invoke/MethodHandles$Lookup;Ljava/lang/String;Ljava/lang/invoke/MethodType;Ljava/lang/String;[Ljava/lang/Object;)Ljava/lang/invoke/CallSite;
      // arguments:
      "\u274c Assembly upload failed for \u0001"
    ]
    ALOAD 3
    CHECKCAST java/lang/Throwable
    INVOKESTATIC android/util/Log.e (Ljava/lang/String;Ljava/lang/String;Ljava/lang/Throwable;)I
    POP
   L90
    LINENUMBER 343 L90
    ALOAD 0
    ALOAD 1
    INVOKEVIRTUAL com/example/rocketplan_android/data/local/entity/ImageProcessorAssemblyEntity.getAssemblyId ()Ljava/lang/String;
    GETSTATIC com/example/rocketplan_android/data/local/entity/AssemblyStatus.FAILED : Lcom/example/rocketplan_android/data/local/entity/AssemblyStatus;
    ALOAD 3
    INVOKEVIRTUAL java/lang/Exception.getMessage ()Ljava/lang/String;
    ALOAD 2
    ICONST_0
    INVOKESTATIC kotlin/jvm/internal/InlineMarker.mark (I)V
    INVOKESPECIAL com/example/rocketplan_android/data/queue/ImageProcessorQueueManager.updateAssemblyStatus (Ljava/lang/String;Lcom/example/rocketplan_android/data/local/entity/AssemblyStatus;Ljava/lang/String;Lkotlin/coroutines/Continuation;)Ljava/lang/Object;
    ICONST_1
    INVOKESTATIC kotlin/jvm/internal/InlineMarker.mark (I)V
    POP
   L91
    LINENUMBER 346 L91
    ALOAD 0
    GETFIELD com/example/rocketplan_android/data/queue/ImageProcessorQueueManager.dao : Lcom/example/rocketplan_android/data/local/dao/ImageProcessorDao;
    ALOAD 1
    INVOKEVIRTUAL com/example/rocketplan_android/data/local/entity/ImageProcessorAssemblyEntity.getAssemblyId ()Ljava/lang/String;
    ALOAD 2
    ICONST_0
    INVOKESTATIC kotlin/jvm/internal/InlineMarker.mark (I)V
    INVOKEINTERFACE com/example/rocketplan_android/data/local/dao/ImageProcessorDao.getAssembly (Ljava/lang/String;Lkotlin/coroutines/Continuation;)Ljava/lang/Object; (itf)
    ICONST_1
    INVOKESTATIC kotlin/jvm/internal/InlineMarker.mark (I)V
    CHECKCAST com/example/rocketplan_android/data/local/entity/ImageProcessorAssemblyEntity
    ASTORE 4
   L92
   L93
    LINENUMBER 347 L93
    ALOAD 4
    IFNULL L94
   L95
    LINENUMBER 348 L95
    ALOAD 0
    ALOAD 4
    INVOKEVIRTUAL com/example/rocketplan_android/data/local/entity/ImageProcessorAssemblyEntity.getRetryCount ()I
    INVOKESPECIAL com/example/rocketplan_android/data/queue/ImageProcessorQueueManager.calculateNextRetryTimeout (I)I
    ISTORE 5
   L96
   L97
    LINENUMBER 349 L97
    INVOKESTATIC java/lang/System.currentTimeMillis ()J
    ILOAD 5
    I2L
    LDC 1000
    LMUL
    LADD
    LSTORE 6
   L98
   L99
    LINENUMBER 351 L99
    ALOAD 4
    LCONST_0
    ACONST_NULL
    ACONST_NULL
    LCONST_0
    ACONST_NULL
    ACONST_NULL
    ICONST_0
    LCONST_0
    LCONST_0
    LCONST_0
    ACONST_NULL
   L100
    LINENUMBER 352 L100
    ALOAD 4
    INVOKEVIRTUAL com/example/rocketplan_android/data/local/entity/ImageProcessorAssemblyEntity.getFailsCount ()I
    ICONST_1
    IADD
   L101
    LINENUMBER 353 L101
    ALOAD 4
    INVOKEVIRTUAL com/example/rocketplan_android/data/local/entity/ImageProcessorAssemblyEntity.getRetryCount ()I
    ICONST_1
    IADD
   L102
    LINENUMBER 354 L102
    LLOAD 6
    INVOKESTATIC kotlin/coroutines/jvm/internal/Boxing.boxLong (J)Ljava/lang/Long;
   L103
    LINENUMBER 355 L103
    ILOAD 5
   L104
    LINENUMBER 351 L104
    NOP
    ICONST_0
    ACONST_NULL
    ACONST_NULL
    LDC 231423
    ACONST_NULL
    INVOKESTATIC com/example/rocketplan_android/data/local/entity/ImageProcessorAssemblyEntity.copy$default (Lcom/example/rocketplan_android/data/local/entity/ImageProcessorAssemblyEntity;JLjava/lang/String;Ljava/lang/Long;JLjava/lang/String;Ljava/lang/String;IJJJLjava/lang/String;IILjava/lang/Long;IZLjava/lang/String;Ljava/lang/Long;ILjava/lang/Object;)Lcom/example/rocketplan_android/data/local/entity/ImageProcessorAssemblyEntity;
    ASTORE 8
   L105
   L106
    LINENUMBER 357 L106
    ALOAD 0
    GETFIELD com/example/rocketplan_android/data/queue/ImageProcessorQueueManager.dao : Lcom/example/rocketplan_android/data/local/dao/ImageProcessorDao;
    ALOAD 8
    ALOAD 2
    ICONST_0
    INVOKESTATIC kotlin/jvm/internal/InlineMarker.mark (I)V
    INVOKEINTERFACE com/example/rocketplan_android/data/local/dao/ImageProcessorDao.updateAssembly (Lcom/example/rocketplan_android/data/local/entity/ImageProcessorAssemblyEntity;Lkotlin/coroutines/Continuation;)Ljava/lang/Object; (itf)
    ICONST_1
    INVOKESTATIC kotlin/jvm/internal/InlineMarker.mark (I)V
    POP
   L107
    LINENUMBER 359 L107
    ALOAD 8
    INVOKEVIRTUAL com/example/rocketplan_android/data/local/entity/ImageProcessorAssemblyEntity.getFailsCount ()I
    BIPUSH 13
    IF_ICMPGE L108
   L109
    LINENUMBER 360 L109
    ALOAD 0
    ILOAD 5
    I2L
    INVOKESPECIAL com/example/rocketplan_android/data/queue/ImageProcessorQueueManager.scheduleOneOffRetry (J)V
   L108
   L110
   L111
   L94
   L112
   L113
    LINENUMBER 364 L113
    ALOAD 0
    ALOAD 1
    INVOKEVIRTUAL com/example/rocketplan_android/data/local/entity/ImageProcessorAssemblyEntity.getAssemblyId ()Ljava/lang/String;
    NOP
    ICONST_0
    ALOAD 3
    INVOKEVIRTUAL java/lang/Exception.getMessage ()Ljava/lang/String;
    ALOAD 2
    ICONST_0
    INVOKESTATIC kotlin/jvm/internal/InlineMarker.mark (I)V
    INVOKESPECIAL com/example/rocketplan_android/data/queue/ImageProcessorQueueManager.onAssemblyCompleted (Ljava/lang/String;ZLjava/lang/String;Lkotlin/coroutines/Continuation;)Ljava/lang/Object;
    ICONST_1
    INVOKESTATIC kotlin/jvm/internal/InlineMarker.mark (I)V
    POP
   L114
   L115
   L86
   L116
    LINENUMBER 366 L116
    NOP
    GETSTATIC kotlin/Unit.INSTANCE : Lkotlin/Unit;
    ARETURN
   L117
    LOCALVARIABLE errorMessage Ljava/lang/String; L15 L21 4
    LOCALVARIABLE $i$a$-filter-ImageProcessorQueueManager$uploadAssembly$pendingPhotos$1\3\749\0 I L40 L43 14
    LOCALVARIABLE it\3 Lcom/example/rocketplan_android/data/local/entity/ImageProcessorPhotoEntity; L39 L43 13
    LOCALVARIABLE element\2 Ljava/lang/Object; L38 L45 12
    LOCALVARIABLE $i$f$filterTo\2\748 I L35 L46 10
    LOCALVARIABLE $this$filterTo\2 Ljava/lang/Iterable; L34 L46 8
    LOCALVARIABLE destination\2 Ljava/util/Collection; L34 L46 9
    LOCALVARIABLE $i$f$filter\1\310 I L33 L50 7
    LOCALVARIABLE $this$filter\1 Ljava/lang/Iterable; L32 L50 6
    LOCALVARIABLE e Ljava/lang/Exception; L76 L80 11
    LOCALVARIABLE photo Lcom/example/rocketplan_android/data/local/entity/ImageProcessorPhotoEntity; L69 L81 9
    LOCALVARIABLE uploadData Lcom/example/rocketplan_android/data/storage/StoredUploadData; L11 L85 3
    LOCALVARIABLE photos Ljava/util/List; L24 L85 4
    LOCALVARIABLE pendingPhotos Ljava/util/List; L52 L85 5
    LOCALVARIABLE successCount I L62 L85 6
    LOCALVARIABLE failureCount I L64 L85 7
    LOCALVARIABLE nextTimeout I L96 L111 5
    LOCALVARIABLE nextRetryAt J L98 L111 6
    LOCALVARIABLE updated Lcom/example/rocketplan_android/data/local/entity/ImageProcessorAssemblyEntity; L105 L111 8
    LOCALVARIABLE currentAssembly Lcom/example/rocketplan_android/data/local/entity/ImageProcessorAssemblyEntity; L92 L114 4
    LOCALVARIABLE e Ljava/lang/Exception; L88 L115 3
    LOCALVARIABLE this Lcom/example/rocketplan_android/data/queue/ImageProcessorQueueManager; L6 L117 0
    LOCALVARIABLE assembly Lcom/example/rocketplan_android/data/local/entity/ImageProcessorAssemblyEntity; L6 L117 1
    LOCALVARIABLE $completion Lkotlin/coroutines/Continuation; L6 L117 2
    MAXSTACK = 26
    MAXLOCALS = 15

File is unknown
The root cause java.lang.OutOfMemoryError was thrown at: org.jetbrains.org.objectweb.asm.tree.analysis.Frame.<init>(Frame.java:78)
	at org.jetbrains.kotlin.codegen.TransformationMethodVisitor.visitEnd(TransformationMethodVisitor.kt:89)
	at org.jetbrains.org.objectweb.asm.tree.MethodNode.accept(MethodNode.java:772)
	at org.jetbrains.kotlin.backend.jvm.codegen.CoroutineCodegenKt.acceptWithStateMachine(CoroutineCodegen.kt:76)
	at org.jetbrains.kotlin.backend.jvm.codegen.ClassCodegen.generateMethod(ClassCodegen.kt:440)
	at org.jetbrains.kotlin.backend.jvm.codegen.ClassCodegen.generate(ClassCodegen.kt:168)
	at org.jetbrains.kotlin.backend.jvm.FileCodegen.lower(JvmPhases.kt:39)
	at org.jetbrains.kotlin.backend.common.phaser.PhaseFactoriesKt.createFilePhase$lambda$4(PhaseFactories.kt:71)
	at org.jetbrains.kotlin.backend.common.phaser.PhaseBuildersKt$createSimpleNamedCompilerPhase$1.phaseBody(PhaseBuilders.kt:69)
	at org.jetbrains.kotlin.backend.common.phaser.SimpleNamedCompilerPhase.phaseBody(CompilerPhase.kt:226)
	at org.jetbrains.kotlin.backend.common.phaser.AbstractNamedCompilerPhase.invoke(CompilerPhase.kt:113)
	at org.jetbrains.kotlin.backend.common.phaser.PerformByIrFilePhase.invokeSequential(performByIrFile.kt:62)
	at org.jetbrains.kotlin.backend.common.phaser.PerformByIrFilePhase.invoke(performByIrFile.kt:52)
	at org.jetbrains.kotlin.backend.common.phaser.PerformByIrFilePhase.invoke(performByIrFile.kt:38)
	at org.jetbrains.kotlin.backend.common.phaser.NamedCompilerPhase.phaseBody(CompilerPhase.kt:166)
	at org.jetbrains.kotlin.backend.common.phaser.AbstractNamedCompilerPhase.invoke(CompilerPhase.kt:113)
	at org.jetbrains.kotlin.backend.common.phaser.CompositePhase.invoke(PhaseBuilders.kt:27)
	at org.jetbrains.kotlin.backend.common.phaser.CompositePhase.invoke(PhaseBuilders.kt:14)
	at org.jetbrains.kotlin.backend.common.phaser.NamedCompilerPhase.phaseBody(CompilerPhase.kt:166)
	at org.jetbrains.kotlin.backend.common.phaser.AbstractNamedCompilerPhase.invoke(CompilerPhase.kt:113)
	at org.jetbrains.kotlin.backend.common.phaser.CompilerPhaseKt.invokeToplevel(CompilerPhase.kt:62)
	at org.jetbrains.kotlin.backend.jvm.JvmIrCodegenFactory.invokeCodegen(JvmIrCodegenFactory.kt:371)
	at org.jetbrains.kotlin.codegen.CodegenFactory.generateModule(CodegenFactory.kt:47)
	at org.jetbrains.kotlin.backend.jvm.JvmIrCodegenFactory.generateModuleInFrontendIRMode(JvmIrCodegenFactory.kt:433)
	at org.jetbrains.kotlin.cli.jvm.compiler.pipeline.JvmCompilerPipelineKt.generateCodeFromIr(jvmCompilerPipeline.kt:246)
	at org.jetbrains.kotlin.cli.jvm.compiler.pipeline.JvmCompilerPipelineKt.compileModulesUsingFrontendIrAndLightTree(jvmCompilerPipeline.kt:142)
	at org.jetbrains.kotlin.cli.jvm.K2JVMCompiler.doExecute(K2JVMCompiler.kt:148)
	at org.jetbrains.kotlin.cli.jvm.K2JVMCompiler.doExecute(K2JVMCompiler.kt:43)
	at org.jetbrains.kotlin.cli.common.CLICompiler.execImpl(CLICompiler.kt:103)
	at org.jetbrains.kotlin.cli.common.CLICompiler.execImpl(CLICompiler.kt:49)
	at org.jetbrains.kotlin.cli.common.CLITool.exec(CLITool.kt:101)
	at org.jetbrains.kotlin.incremental.IncrementalJvmCompilerRunner.runCompiler(IncrementalJvmCompilerRunner.kt:464)
	at org.jetbrains.kotlin.incremental.IncrementalJvmCompilerRunner.runCompiler(IncrementalJvmCompilerRunner.kt:73)
	at org.jetbrains.kotlin.incremental.IncrementalCompilerRunner.doCompile(IncrementalCompilerRunner.kt:506)
	at org.jetbrains.kotlin.incremental.IncrementalCompilerRunner.compileImpl(IncrementalCompilerRunner.kt:423)
	at org.jetbrains.kotlin.incremental.IncrementalCompilerRunner.compileNonIncrementally(IncrementalCompilerRunner.kt:301)
	at org.jetbrains.kotlin.incremental.IncrementalCompilerRunner.compile(IncrementalCompilerRunner.kt:129)
	at org.jetbrains.kotlin.daemon.CompileServiceImplBase.execIncrementalCompiler(CompileServiceImpl.kt:675)
	at org.jetbrains.kotlin.daemon.CompileServiceImplBase.access$execIncrementalCompiler(CompileServiceImpl.kt:92)
	at org.jetbrains.kotlin.daemon.CompileServiceImpl.compile(CompileServiceImpl.kt:1660)
	at java.base/jdk.internal.reflect.DirectMethodHandleAccessor.invoke(DirectMethodHandleAccessor.java:103)
	at java.base/java.lang.reflect.Method.invoke(Method.java:580)
	at java.rmi/sun.rmi.server.UnicastServerRef.dispatch(UnicastServerRef.java:360)
	at java.rmi/sun.rmi.transport.Transport$1.run(Transport.java:200)
	at java.rmi/sun.rmi.transport.Transport$1.run(Transport.java:197)
	at java.base/java.security.AccessController.doPrivileged(AccessController.java:714)
	at java.rmi/sun.rmi.transport.Transport.serviceCall(Transport.java:196)
	at java.rmi/sun.rmi.transport.tcp.TCPTransport.handleMessages(TCPTransport.java:598)
	at java.rmi/sun.rmi.transport.tcp.TCPTransport$ConnectionHandler.run0(TCPTransport.java:844)
	at java.rmi/sun.rmi.transport.tcp.TCPTransport$ConnectionHandler.lambda$run$0(TCPTransport.java:721)
	at java.base/java.security.AccessController.doPrivileged(AccessController.java:400)
	at java.rmi/sun.rmi.transport.tcp.TCPTransport$ConnectionHandler.run(TCPTransport.java:720)
	at java.base/java.util.concurrent.ThreadPoolExecutor.runWorker(ThreadPoolExecutor.java:1144)
	at java.base/java.util.concurrent.ThreadPoolExecutor$Worker.run(ThreadPoolExecutor.java:642)
	at java.base/java.lang.Thread.run(Thread.java:1583)
Caused by: java.lang.OutOfMemoryError: Java heap space
	at org.jetbrains.org.objectweb.asm.tree.analysis.Frame.<init>(Frame.java:78)
	at org.jetbrains.kotlin.codegen.optimization.common.FastMethodAnalyzer._init_$lambda$0(FastMethodAnalyzer.kt:47)
	at org.jetbrains.kotlin.codegen.optimization.common.FastMethodAnalyzer$$Lambda/0x0000000133ed9b50.invoke(Unknown Source)
	at org.jetbrains.kotlin.codegen.optimization.common.FastAnalyzer.fullMergeControlFlowEdge(FastAnalyzer.kt:233)
	at org.jetbrains.kotlin.codegen.optimization.common.FastAnalyzer.mergeControlFlowEdge(FastAnalyzer.kt:216)
	at org.jetbrains.kotlin.codegen.optimization.common.FastAnalyzer.processControlFlowEdge(FastAnalyzer.kt:208)
	at org.jetbrains.kotlin.codegen.optimization.common.FastAnalyzer.processControlFlowEdge$default(FastAnalyzer.kt:206)
	at org.jetbrains.kotlin.codegen.optimization.common.FastAnalyzer.visitOpInsn(FastAnalyzer.kt:292)
	at org.jetbrains.kotlin.codegen.optimization.common.FastAnalyzer.visitMeaningfulInstruction(FastAnalyzer.kt:281)
	at org.jetbrains.kotlin.codegen.optimization.common.FastAnalyzer.analyzeInstruction(FastAnalyzer.kt:113)
	at org.jetbrains.kotlin.codegen.optimization.common.FastAnalyzer.analyzeMainLoop(FastAnalyzer.kt:74)
	at org.jetbrains.kotlin.codegen.optimization.common.FastAnalyzer.analyze(FastAnalyzer.kt:53)
	at org.jetbrains.kotlin.codegen.optimization.transformer.MethodTransformer.analyze(MethodTransformer.java:49)
	at org.jetbrains.kotlin.codegen.coroutines.TailCallOptimizationKt.allSuspensionPointsAreTailCalls(TailCallOptimization.kt:24)
	at org.jetbrains.kotlin.codegen.coroutines.CoroutineTransformerMethodVisitor.performTransformations(CoroutineTransformerMethodVisitor.kt:99)
	at org.jetbrains.kotlin.codegen.TransformationMethodVisitor.visitEnd(TransformationMethodVisitor.kt:67)
	at org.jetbrains.org.objectweb.asm.tree.MethodNode.accept(MethodNode.java:772)
	at org.jetbrains.kotlin.backend.jvm.codegen.CoroutineCodegenKt.acceptWithStateMachine(CoroutineCodegen.kt:76)
	at org.jetbrains.kotlin.backend.jvm.codegen.ClassCodegen.generateMethod(ClassCodegen.kt:440)
	at org.jetbrains.kotlin.backend.jvm.codegen.ClassCodegen.generate(ClassCodegen.kt:168)
	at org.jetbrains.kotlin.backend.jvm.FileCodegen.lower(JvmPhases.kt:39)
	at org.jetbrains.kotlin.backend.common.phaser.PhaseFactoriesKt.createFilePhase$lambda$4(PhaseFactories.kt:71)
	at org.jetbrains.kotlin.backend.common.phaser.PhaseFactoriesKt$$Lambda/0x0000000133137c38.invoke(Unknown Source)
	at org.jetbrains.kotlin.backend.common.phaser.PhaseBuildersKt$createSimpleNamedCompilerPhase$1.phaseBody(PhaseBuilders.kt:69)
	at org.jetbrains.kotlin.backend.common.phaser.SimpleNamedCompilerPhase.phaseBody(CompilerPhase.kt:226)
	at org.jetbrains.kotlin.backend.common.phaser.AbstractNamedCompilerPhase.invoke(CompilerPhase.kt:113)
	at org.jetbrains.kotlin.backend.common.phaser.PerformByIrFilePhase.invokeSequential(performByIrFile.kt:62)
	at org.jetbrains.kotlin.backend.common.phaser.PerformByIrFilePhase.invoke(performByIrFile.kt:52)
	at org.jetbrains.kotlin.backend.common.phaser.PerformByIrFilePhase.invoke(performByIrFile.kt:38)
	at org.jetbrains.kotlin.backend.common.phaser.NamedCompilerPhase.phaseBody(CompilerPhase.kt:166)
	at org.jetbrains.kotlin.backend.common.phaser.AbstractNamedCompilerPhase.invoke(CompilerPhase.kt:113)
	at org.jetbrains.kotlin.backend.common.phaser.CompositePhase.invoke(PhaseBuilders.kt:27)


